{
  "display": {
    "icon": {
      "id": "mintyirlplanets:brimstone"
    },
    "title": {
      "translate": "advancements.it_came_from_the_depths_of_hell.title"
    },
    "description": {
      "translate": "advancements.it_came_from_the_depths_of_hell.descr"
    },
    "frame": "task",
    "show_toast": true,
    "announce_to_chat": true,
    "hidden": false
  },
  "criteria": {
    "it_came_from_the_depths_of_hell_0": {
      "trigger": "minecraft:inventory_changed",
      "conditions": {
        "items": [
          {
            "items": "mintyirlplanets:brimstone_ore",
            "count": {
              "min": 1,
              "max": 100
            }
          }
        ]
      }
    }
  },
  "rewards": {
    "experience": 0,
    "recipes": [
      "mintyirlplanets:brimstone_ore_block_recipe",
      "mintyirlplanets:brimstone_block_ore_recipe",
      "mintyirlplanets:brimstone_ore_smelting",
      "mintyirlplanets:brimstone_pickaxe_recipe",
      "mintyirlplanets:brimstone_axe_recipe",
      "mintyirlplanets:brimstone_sword_recipe",
      "mintyirlplanets:brimstone_shovel_recipe",
      "mintyirlplanets:brimstone_hoe_recipe",
      "mintyirlplanets:brimstone_armor_helmet_recipe",
      "mintyirlplanets:brimstone_armor_chestplate_recipe",
      "mintyirlplanets:brimstone_armor_leggings_recipe",
      "mintyirlplanets:brimstone_armor_boots_recipe"
    ]
  },
  "parent": "mintyirlplanets:resonance"
}