{
  "type": "minecraft:entity",
  "pools": [
    {
      "rolls": {
        "min": 0,
        "max": 1
      },
      "entries": [
        {
          "type": "minecraft:item",
          "name": "mintyirlplanets:strange_energy",
          "weight": 1,
          "functions": [
            {
              "function": "minecraft:set_count",
              "count": {
                "min": 0,
                "max": 1
              }
            }
          ]
        }
      ]
    },
    {
      "rolls": 1,
      "entries": [
        {
          "type": "minecraft:item",
          "name": "mintyirlplanets:tv_meat",
          "weight": 1,
          "functions": [
            {
              "function": "minecraft:set_count",
              "count": {
                "min": 1,
                "max": 3
              }
            }
          ]
        }
      ]
    }
  ],
  "random_sequence": "mintyirlplanets:entities/eyezor"
}